treelock.py
treelock-0.0.17.dist-info/LICENSE
treelock-0.0.17.dist-info/METADATA
treelock-0.0.17.dist-info/WHEEL
treelock-0.0.17.dist-info/top_level.txt
treelock-0.0.17.dist-info/RECORD
