Metadata-Version: 2.1
Name: treelock
Version: 0.0.17
Summary: Fast read/write sub-tree locking for asyncio Python
Home-page: https://github.com/michalc/treelock
Author: Michal Charemza
Author-email: michal@charemza.name
License: UNKNOWN
Platform: UNKNOWN
Classifier: Programming Language :: Python :: 3
Classifier: License :: OSI Approved :: MIT License
Classifier: Operating System :: OS Independent
Classifier: Framework :: AsyncIO
Requires-Python: >=3.5
Requires-Dist: fifolock
